pytautulli/__init__.py
pytautulli/client.py
pytautulli/const.py
pytautulli/decorator.py
pytautulli/exceptions.py
pytautulli/models/__init__.py
pytautulli/models/activity.py
pytautulli/models/base.py
pytautulli/models/const.py
pytautulli/models/home_stats.py
pytautulli/models/host_configuration.py
pytautulli/models/response.py
pytautulli/models/server_info.py
pytautulli/models/session.py
pytautulli/models/user.py
pytautulli-23.1.1.dist-info/LICENSE
pytautulli-23.1.1.dist-info/METADATA
pytautulli-23.1.1.dist-info/WHEEL
pytautulli-23.1.1.dist-info/top_level.txt
pytautulli-23.1.1.dist-info/RECORD
