Metadata-Version: 2.1
Name: pytautulli
Version: 23.1.1
Summary: Python API wrapper for Tautulli.
Home-page: https://github.com/ludeeus/pytautulli
Author: Joakim Sorensen
Author-email: hi@ludeeus.dev
License: MIT license
Keywords: pytautulli,tautulli,plex
Classifier: Intended Audience :: Developers
Classifier: License :: OSI Approved :: MIT License
Classifier: Natural Language :: English
Classifier: Programming Language :: Python :: 3
Classifier: Programming Language :: Python :: 3.8
Classifier: Programming Language :: Python :: 3.9
Classifier: Programming Language :: Python :: 3.10
Classifier: Topic :: Software Development :: Libraries :: Python Modules
Requires-Python: >=3.8.0
License-File: LICENSE
